eddy_bot/__init__.py
eddy_bot/cli.py
eddy_bot/eddy_bot.py
eddy_bot/logger.py
eddy_bot/utils.py
eddy_bot/vars.py
eddy_bot/crawlers/__init__.py
eddy_bot/crawlers/facebook/__init__.py
eddy_bot/crawlers/instagram/__init__.py
eddy_bot/crawlers/instagram/instagram_bot.py
eddy_bot/crawlers/tiktok/__init__.py
eddy_bot/crawlers/tiktok/tiktok_bot.py
eddy_bot/crawlers/twitter/__init__.py
eddy_bot/crawlers/twitter/twitter_bot.py
eddy_bot/models/__init__.py
eddy_bot/models/request_bot.py
eddy_bot/models/selenium_bot.py
eddy_bot/models/social_media_bot.py
eddy_bot-0.1.0.dist-info/AUTHORS.rst
eddy_bot-0.1.0.dist-info/LICENSE
eddy_bot-0.1.0.dist-info/METADATA
eddy_bot-0.1.0.dist-info/WHEEL
eddy_bot-0.1.0.dist-info/entry_points.txt
eddy_bot-0.1.0.dist-info/top_level.txt
eddy_bot-0.1.0.dist-info/RECORD
