Metadata-Version: 2.1
Name: eddy-bot
Version: 0.1.0
Summary: Eddy Bot is a command line interface to interact with social media. Currently supports Twitter, TikTok and Instagram.
Home-page: https://github.com/joaoheron/eddy_bot
Author: Joao Heron
Author-email: joao@mail.com
License: Apache Software License 2.0
Keywords: eddy_bot
Platform: UNKNOWN
Classifier: Development Status :: 2 - Pre-Alpha
Classifier: Intended Audience :: Developers
Classifier: License :: OSI Approved :: Apache Software License
Classifier: Natural Language :: English
Classifier: Programming Language :: Python :: 3
Classifier: Programming Language :: Python :: 3.6
Classifier: Programming Language :: Python :: 3.7
Classifier: Programming Language :: Python :: 3.8
Requires-Python: >=3.6
Requires-Dist: Click (>=7.0)
Requires-Dist: Sphinx (>=4.1.1)
Requires-Dist: cryptography (>=3.4.7)
Requires-Dist: flake8 (>=3.7.8)
Requires-Dist: numpy (>=1.21.0)
Requires-Dist: pip (>=20.0.2)
Requires-Dist: pyaml (>=20.4.0)
Requires-Dist: python-dotenv (>=0.17.0)
Requires-Dist: selenium (>=3.141.0)
Requires-Dist: tweepy (>=3.10.0)
Requires-Dist: twine (>=3.4.1)
